vogel/__init__.py
vogel/preprocessing/__init__.py
vogel/preprocessing/preprocessing.py
vogel/train/__init__.py
vogel/train/train.py
vogel/utils/__init__.py
vogel/utils/utils.py
vogel/utils/stats/__init__.py
vogel/utils/stats/stats.py
vogel-0.2.4.dist-info/LICENSE
vogel-0.2.4.dist-info/METADATA
vogel-0.2.4.dist-info/WHEEL
vogel-0.2.4.dist-info/top_level.txt
vogel-0.2.4.dist-info/RECORD
